[
  {
    "date": "2020-01-04",
    "event": "Torni-Turnaus, Kuopio FIN",
    "discipline": "Epee Men's Senior Individual",
    "stage": "DE",
    "round": "A",
    "match": "A32",
    "opponent": "RISSANEN Joona (FIN)",
    "opponentUrl": "/en/biography/athlete/356293",
    "win": false,
    "scoreOwn": 10,
    "scoreOpponent": 15
  },
  {
    "date": "2020-01-04",
    "event": "Torni-Turnaus, Kuopio FIN",
    "discipline": "Epee Men's Senior Individual",
    "stage": "Round",
    "round": "",
    "match": "2",
    "opponent": "SEPPÄNEN Ilkka (FIN)",
    "opponentUrl": "/en/biography/athlete/50455",
    "win": false,
    "scoreOwn": 4,
    "scoreOpponent": 5
  },
  {
    "date": "2020-01-04",
    "event": "Torni-Turnaus, Kuopio FIN",
    "discipline": "Epee Men's Senior Individual",
    "stage": "Round",
    "round": "",
    "match": "2",
    "opponent": "SOININEN Sami (FIN)",
    "opponentUrl": "/en/biography/athlete/392495",
    "win": false,
    "scoreOwn": 2,
    "scoreOpponent": 5
  },
  {
    "date": "2020-01-04",
    "event": "Torni-Turnaus, Kuopio FIN",
    "discipline": "Epee Men's Senior Individual",
    "stage": "Round",
    "round": "",
    "match": "2",
    "opponent": "GRÄSBECK Gunnar (FIN)",
    "opponentUrl": "/en/biography/athlete/53395",
    "win": false,
    "scoreOwn": 3,
    "scoreOpponent": 5
  },
  {
    "date": "2020-01-04",
    "event": "Torni-Turnaus, Kuopio FIN",
    "discipline": "Epee Men's Senior Individual",
    "stage": "Round",
    "round": "",
    "match": "2",
    "opponent": "RISSANEN Joona (FIN)",
    "opponentUrl": "/en/biography/athlete/356293",
    "win": true,
    "scoreOwn": 5,
    "scoreOpponent": 4
  },
  {
    "date": "2020-01-04",
    "event": "Torni-Turnaus, Kuopio FIN",
    "discipline": "Epee Men's Senior Individual",
    "stage": "Round",
    "round": "",
    "match": "2",
    "opponent": "KESKINIVA Arto (FIN)",
    "opponentUrl": "/en/biography/athlete/306331",
    "win": true,
    "scoreOwn": 5,
    "scoreOpponent": 4
  },
  {
    "date": "2020-01-04",
    "event": "Torni-Turnaus, Kuopio FIN",
    "discipline": "Epee Men's Senior Individual",
    "stage": "Round",
    "round": "",
    "match": "2",
    "opponent": "JÄNTTI Jan (FIN)",
    "opponentUrl": "/en/biography/athlete/380178",
    "win": false,
    "scoreOwn": 2,
    "scoreOpponent": 5
  },
  {
    "date": "2019-10-12",
    "event": "Helsinki Masters, Helsinki FIN",
    "discipline": "Epee Men's U20 Individual",
    "stage": "DE",
    "round": "A",
    "match": "A32",
    "opponent": "KERÄNEN Miika (FIN)",
    "opponentUrl": "/en/biography/athlete/327163",
    "win": false,
    "scoreOwn": 6,
    "scoreOpponent": 15
  },
  {
    "date": "2019-10-12",
    "event": "Helsinki Masters, Helsinki FIN",
    "discipline": "Epee Men's U20 Individual",
    "stage": "Round",
    "round": "",
    "match": "3",
    "opponent": "PIRHONEN Petri (FIN)",
    "opponentUrl": "/en/biography/athlete/326308",
    "win": false,
    "scoreOwn": 2,
    "scoreOpponent": 5
  },
  {
    "date": "2019-10-12",
    "event": "Helsinki Masters, Helsinki FIN",
    "discipline": "Epee Men's U20 Individual",
    "stage": "Round",
    "round": "",
    "match": "3",
    "opponent": "KERÄNEN Miika (FIN)",
    "opponentUrl": "/en/biography/athlete/327163",
    "win": false,
    "scoreOwn": 1,
    "scoreOpponent": 5
  },
  {
    "date": "2019-10-12",
    "event": "Helsinki Masters, Helsinki FIN",
    "discipline": "Epee Men's U20 Individual",
    "stage": "Round",
    "round": "",
    "match": "3",
    "opponent": "JUSSILA Johannes (FIN)",
    "opponentUrl": "/en/biography/athlete/319782",
    "win": false,
    "scoreOwn": 1,
    "scoreOpponent": 5
  },
  {
    "date": "2019-10-12",
    "event": "Helsinki Masters, Helsinki FIN",
    "discipline": "Epee Men's U20 Individual",
    "stage": "Round",
    "round": "",
    "match": "3",
    "opponent": "MEIER Jaan (EST)",
    "opponentUrl": "/en/biography/athlete/398103",
    "win": false,
    "scoreOwn": 2,
    "scoreOpponent": 5
  },
  {
    "date": "2019-10-12",
    "event": "Helsinki Masters, Helsinki FIN",
    "discipline": "Epee Men's U20 Individual",
    "stage": "Round",
    "round": "",
    "match": "3",
    "opponent": "JUTILA Julius (FIN)",
    "opponentUrl": "/en/biography/athlete/334008",
    "win": false,
    "scoreOwn": 1,
    "scoreOpponent": 5
  },
  {
    "date": "2019-10-12",
    "event": "Helsinki Masters, Helsinki FIN",
    "discipline": "Epee Men's U20 Individual",
    "stage": "Round",
    "round": "",
    "match": "3",
    "opponent": "ZABELIN Eldar (EST)",
    "opponentUrl": "/en/biography/athlete/390707",
    "win": false,
    "scoreOwn": 2,
    "scoreOpponent": 5
  },
  {
    "date": "2019-01-26",
    "event": "Espoo Fencing Challenge, Espoo (Helsinki) FIN",
    "discipline": "Epee Men's U17 Individual",
    "stage": "Round",
    "round": "",
    "match": "2",
    "opponent": "REDLICH Tobias Anon (DEN)",
    "opponentUrl": "/en/biography/athlete/redlich-tobias-anon-1",
    "win": false,
    "scoreOwn": 4,
    "scoreOpponent": 5
  },
  {
    "date": "2019-01-26",
    "event": "Espoo Fencing Challenge, Espoo (Helsinki) FIN",
    "discipline": "Epee Men's U17 Individual",
    "stage": "Round",
    "round": "",
    "match": "2",
    "opponent": "MIRINUKS Ervins (LAT)",
    "opponentUrl": "/en/biography/athlete/mirinuks-ervins",
    "win": true,
    "scoreOwn": 5,
    "scoreOpponent": 3
  },
  {
    "date": "2019-01-26",
    "event": "Espoo Fencing Challenge, Espoo (Helsinki) FIN",
    "discipline": "Epee Men's U17 Individual",
    "stage": "Round",
    "round": "",
    "match": "2",
    "opponent": "FURUHASHI Ryoki (JPN)",
    "opponentUrl": "/en/biography/athlete/395862",
    "win": false,
    "scoreOwn": 1,
    "scoreOpponent": 5
  },
  {
    "date": "2019-01-26",
    "event": "Espoo Fencing Challenge, Espoo (Helsinki) FIN",
    "discipline": "Epee Men's U17 Individual",
    "stage": "Round",
    "round": "",
    "match": "2",
    "opponent": "IHRE-THOMASON Axel (SWE)",
    "opponentUrl": "/en/biography/athlete/319546",
    "win": false,
    "scoreOwn": 2,
    "scoreOpponent": 5
  },
  {
    "date": "2019-01-26",
    "event": "Espoo Fencing Challenge, Espoo (Helsinki) FIN",
    "discipline": "Epee Men's U17 Individual",
    "stage": "Round",
    "round": "",
    "match": "2",
    "opponent": "CARUSI Giacomo (ITA)",
    "opponentUrl": "/en/biography/athlete/395850",
    "win": false,
    "scoreOwn": 4,
    "scoreOpponent": 5
  }
]