[
  {
    "date": "4/15/23",
    "event": "Kerttula Memorial, Helsinki FIN",
    "discipline": "Foil Women's Senior Individual",
    "stage": "Round",
    "round": "",
    "match": "1",
    "opponent": "DEGERMAN Ruusa (FIN)",
    "opponentUrl": "/en/biography/athlete/118764",
    "win": false,
    "scoreOwn": 3,
    "scoreOpponent": 5
  },
  {
    "date": "4/15/23",
    "event": "Kerttula Memorial, Helsinki FIN",
    "discipline": "Foil Women's Senior Individual",
    "stage": "Round",
    "round": "",
    "match": "1",
    "opponent": "SINIOJA Aino (FIN)",
    "opponentUrl": "/en/biography/athlete/sinioja-aino",
    "win": false,
    "scoreOwn": 1,
    "scoreOpponent": 5
  },
  {
    "date": "4/15/23",
    "event": "Kerttula Memorial, Helsinki FIN",
    "discipline": "Foil Women's Senior Individual",
    "stage": "Round",
    "round": "",
    "match": "1",
    "opponent": "KURTTILA Sara (FIN)",
    "opponentUrl": "/en/biography/athlete/340800",
    "win": false,
    "scoreOwn": 2,
    "scoreOpponent": 5
  },
  {
    "date": "4/15/23",
    "event": "Kerttula Memorial, Helsinki FIN",
    "discipline": "Foil Women's Senior Individual",
    "stage": "Round",
    "round": "",
    "match": "1",
    "opponent": "HONKANEN Anniina (FIN)",
    "opponentUrl": "/en/biography/athlete/349670",
    "win": false,
    "scoreOwn": 0,
    "scoreOpponent": 5
  },
  {
    "date": "4/15/23",
    "event": "Kerttula Memorial, Helsinki FIN",
    "discipline": "Foil Women's Senior Individual",
    "stage": "Round",
    "round": "",
    "match": "1",
    "opponent": "HEINO Anna (FIN)",
    "opponentUrl": "/en/biography/athlete/392379",
    "win": false,
    "scoreOwn": 2,
    "scoreOpponent": 5
  },
  {
    "date": "4/15/23",
    "event": "Kerttula Memorial, Helsinki FIN",
    "discipline": "Foil Women's Senior Individual",
    "stage": "Round",
    "round": "",
    "match": "1",
    "opponent": "PALMERIO Leonie (GER)",
    "opponentUrl": "/en/biography/athlete/palmerio-leonie",
    "win": false,
    "scoreOwn": 2,
    "scoreOpponent": 5
  },
  {
    "date": "4/15/23",
    "event": "Kerttula Memorial, Helsinki FIN",
    "discipline": "Foil Women's Senior Individual",
    "stage": "Round",
    "round": "",
    "match": "1",
    "opponent": "KARJALAINEN Veera (FIN)",
    "opponentUrl": "/en/biography/athlete/karjalainen-veera",
    "win": false,
    "scoreOwn": 4,
    "scoreOpponent": 5
  },
  {
    "date": "4/15/23",
    "event": "Kerttula Memorial, Helsinki FIN",
    "discipline": "Foil Women's Senior Individual",
    "stage": "Round",
    "round": "",
    "match": "1",
    "opponent": "HAUKKALA Sanna (FIN)",
    "opponentUrl": "/en/biography/athlete/haukkala-sanna",
    "win": false,
    "scoreOwn": 3,
    "scoreOpponent": 5
  },
  {
    "date": "11/5/22",
    "event": "YM Juhlakilpailu, Helsinki FIN",
    "discipline": "Epee Women's Senior Individual",
    "stage": "DE",
    "round": "A",
    "match": "A32",
    "opponent": "LUNDELL Moa Ruut Maleena (FIN)",
    "opponentUrl": "/en/biography/athlete/lundell-moa-ruut-maleena",
    "win": false,
    "scoreOwn": 7,
    "scoreOpponent": 15
  },
  {
    "date": "11/5/22",
    "event": "YM Juhlakilpailu, Helsinki FIN",
    "discipline": "Epee Women's Senior Individual",
    "stage": "Round",
    "round": "",
    "match": "4",
    "opponent": "POLKKO Seija (FIN)",
    "opponentUrl": "/en/biography/athlete/56889",
    "win": true,
    "scoreOwn": 5,
    "scoreOpponent": 1
  },
  {
    "date": "11/5/22",
    "event": "YM Juhlakilpailu, Helsinki FIN",
    "discipline": "Epee Women's Senior Individual",
    "stage": "Round",
    "round": "",
    "match": "4",
    "opponent": "LUNDELL Moa Ruut Maleena (FIN)",
    "opponentUrl": "/en/biography/athlete/lundell-moa-ruut-maleena",
    "win": false,
    "scoreOwn": 3,
    "scoreOpponent": 5
  },
  {
    "date": "11/5/22",
    "event": "YM Juhlakilpailu, Helsinki FIN",
    "discipline": "Epee Women's Senior Individual",
    "stage": "Round",
    "round": "",
    "match": "4",
    "opponent": "SALMINEN Laura (FIN)",
    "opponentUrl": "/en/biography/athlete/123726",
    "win": false,
    "scoreOwn": 0,
    "scoreOpponent": 5
  },
  {
    "date": "11/5/22",
    "event": "YM Juhlakilpailu, Helsinki FIN",
    "discipline": "Epee Women's Senior Individual",
    "stage": "Round",
    "round": "",
    "match": "4",
    "opponent": "WETHERILL Hilla (FIN)",
    "opponentUrl": "/en/biography/athlete/wetherill-hilla",
    "win": true,
    "scoreOwn": 5,
    "scoreOpponent": 3
  },
  {
    "date": "11/5/22",
    "event": "YM Juhlakilpailu, Helsinki FIN",
    "discipline": "Epee Women's Senior Individual",
    "stage": "Round",
    "round": "",
    "match": "4",
    "opponent": "RITAKALLIO Rilla (FIN)",
    "opponentUrl": "/en/biography/athlete/ritakallio-rilla",
    "win": false,
    "scoreOwn": 2,
    "scoreOpponent": 5
  }
]