[
  {
    "date": "2021-10-23",
    "event": "Nordic Championships, Espoo FIN",
    "discipline": "Sabre Men's U17 Individual",
    "stage": "DE",
    "round": "A",
    "match": "A32",
    "opponent": "HREINSSON Ymir Darri (ISL)",
    "opponentUrl": "/en/biography/athlete/hreinsson-ymir-darri",
    "win": false,
    "scoreOwn": 11,
    "scoreOpponent": 15
  },
  {
    "date": "2021-10-23",
    "event": "Nordic Championships, Espoo FIN",
    "discipline": "Sabre Men's U17 Individual",
    "stage": "Round",
    "round": "",
    "match": "1",
    "opponent": "MELNIK Artemi (EST)",
    "opponentUrl": "/en/biography/athlete/melnik-artemi",
    "win": false,
    "scoreOwn": 1,
    "scoreOpponent": 5
  },
  {
    "date": "2021-10-23",
    "event": "Nordic Championships, Espoo FIN",
    "discipline": "Sabre Men's U17 Individual",
    "stage": "Round",
    "round": "",
    "match": "1",
    "opponent": "KURIR Tobias Neumann (DEN)",
    "opponentUrl": "/en/biography/athlete/359391",
    "win": false,
    "scoreOwn": 3,
    "scoreOpponent": 5
  },
  {
    "date": "2021-10-23",
    "event": "Nordic Championships, Espoo FIN",
    "discipline": "Sabre Men's U17 Individual",
    "stage": "Round",
    "round": "",
    "match": "1",
    "opponent": "LEHMANN ANDERSSON Johannes (DEN)",
    "opponentUrl": "/en/biography/athlete/353394",
    "win": false,
    "scoreOwn": 0,
    "scoreOpponent": 5
  },
  {
    "date": "2021-10-23",
    "event": "Nordic Championships, Espoo FIN",
    "discipline": "Sabre Men's U17 Individual",
    "stage": "Round",
    "round": "",
    "match": "1",
    "opponent": "HREINSSON Ymir Darri (ISL)",
    "opponentUrl": "/en/biography/athlete/hreinsson-ymir-darri",
    "win": false,
    "scoreOwn": 1,
    "scoreOpponent": 5
  },
  {
    "date": "2021-10-23",
    "event": "Nordic Championships, Espoo FIN",
    "discipline": "Sabre Men's U17 Individual",
    "stage": "Round",
    "round": "",
    "match": "1",
    "opponent": "PERSSON Malte (SWE)",
    "opponentUrl": "/en/biography/athlete/persson-malte",
    "win": false,
    "scoreOwn": 0,
    "scoreOpponent": 5
  },
  {
    "date": "2021-10-23",
    "event": "Nordic Championships, Espoo FIN",
    "discipline": "Sabre Men's U17 Individual",
    "stage": "Round",
    "round": "",
    "match": "1",
    "opponent": "IVANOV Aleksandr (EST)",
    "opponentUrl": "/en/biography/athlete/ivanov-aleksandr",
    "win": false,
    "scoreOwn": 0,
    "scoreOpponent": 5
  },
  {
    "date": "2021-10-23",
    "event": "Nordic Championships, Espoo FIN",
    "discipline": "Sabre Men's U17 Individual",
    "stage": "Round",
    "round": "",
    "match": "1",
    "opponent": "PEREZ VILLALBA Leo (FIN)",
    "opponentUrl": "/en/biography/athlete/perez-villalba-leo",
    "win": false,
    "scoreOwn": 2,
    "scoreOpponent": 5
  }
]